[
  {
    "id": "UV001",
    "name": "Nguyễn Hoàng Phúc",
    "email": "phuc.nguyen@gmail.com",
    "phone": "0901 111 222",
    "jobPostingId": "JP001",
    "orgNodeId": "pos-dev-be",
    "source": "linkedin",
    "applyDate": "12/06/2026",
    "status": "interviewed",
    "cvUrl": "",
    "notes": "Ứng viên tiềm năng, kỹ năng Node.js tốt, hỏi lương 22-25M",
    "interviewDate": "20/06/2026",
    "result": "Đạt — chờ offer"
  },
  {
    "id": "UV002",
    "name": "Trần Minh Khoa",
    "email": "khoa.tran@gmail.com",
    "phone": "0912 333 444",
    "jobPostingId": "JP001",
    "orgNodeId": "pos-dev-be",
    "source": "website",
    "applyDate": "14/06/2026",
    "status": "offered",
    "cvUrl": "",
    "notes": "5 năm kinh nghiệm, yêu cầu 28-30M",
    "interviewDate": "22/06/2026",
    "result": "Đạt — đã gửi offer ngày 24/06"
  },
  {
    "id": "UV003",
    "name": "Lê Văn Dũng",
    "email": "dung.le@gmail.com",
    "phone": "0923 555 666",
    "jobPostingId": "JP001",
    "orgNodeId": "pos-dev-be",
    "source": "referral",
    "applyDate": "11/06/2026",
    "status": "rejected",
    "cvUrl": "",
    "notes": "Không đủ yêu cầu kỹ thuật, kinh nghiệm dưới 1 năm",
    "interviewDate": "18/06/2026",
    "result": "Không đạt vòng kỹ thuật"
  },
  {
    "id": "UV004",
    "name": "Phạm Thị Thu Thảo",
    "email": "thao.pham@gmail.com",
    "phone": "0934 777 888",
    "jobPostingId": "JP002",
    "orgNodeId": "pos-rec-spec",
    "source": "linkedin",
    "applyDate": "18/06/2026",
    "status": "screening",
    "cvUrl": "",
    "notes": "3 năm tuyển dụng IT, từng làm headhunt",
    "interviewDate": "",
    "result": ""
  },
  {
    "id": "UV005",
    "name": "Võ Thị Hà",
    "email": "ha.vo@gmail.com",
    "phone": "0945 999 000",
    "jobPostingId": "JP003",
    "orgNodeId": "pos-dev-intern",
    "source": "website",
    "applyDate": "05/06/2026",
    "status": "applied",
    "cvUrl": "",
    "notes": "Sinh viên năm 4 ĐH Bách Khoa, GPA 3.5/4.0",
    "interviewDate": "",
    "result": ""
  },
  {
    "id": "UV006",
    "name": "Đinh Văn Tài",
    "email": "tai.dinh@gmail.com",
    "phone": "0956 111 333",
    "jobPostingId": "JP003",
    "orgNodeId": "pos-dev-intern",
    "source": "referral",
    "applyDate": "03/06/2026",
    "status": "accepted",
    "cvUrl": "",
    "notes": "Được giới thiệu bởi NV002. Nhận vào thực tập từ 01/07/2026.",
    "interviewDate": "10/06/2026",
    "result": "Đạt — onboard 01/07/2026"
  }
]
